delay/__init__.py
delay/delay.py
delay/timer.py
delay_decorator-1.0.1.dist-info/DESCRIPTION.rst
delay_decorator-1.0.1.dist-info/METADATA
delay_decorator-1.0.1.dist-info/RECORD
delay_decorator-1.0.1.dist-info/WHEEL
delay_decorator-1.0.1.dist-info/metadata.json
delay_decorator-1.0.1.dist-info/top_level.txt
