Metadata-Version: 2.0
Name: delay-decorator
Version: 1.0.1
Summary: A python Function / Method delay executing system base on function Decorators.
Home-page: https://github.com/hustcc/wrapcache
Author: pangbo
Author-email: pangbo@gmail.com
License: MIT
Keywords: delay,decorator,python,schedule
Platform: UNKNOWN
Classifier: Intended Audience :: Developers
Classifier: License :: OSI Approved :: MIT License
Classifier: Operating System :: OS Independent
Classifier: Programming Language :: Python
Classifier: Natural Language :: Chinese (Simplified)
Classifier: Natural Language :: Chinese (Traditional)
Classifier: Natural Language :: English
Classifier: Programming Language :: Python
Classifier: Programming Language :: Python :: 2
Classifier: Programming Language :: Python :: 2.7
Classifier: Programming Language :: Python :: 3
Classifier: Programming Language :: Python :: 3.2
Classifier: Programming Language :: Python :: 3.3
Classifier: Programming Language :: Python :: 3.4
Classifier: Programming Language :: Python :: 3.5
Classifier: Topic :: Utilities
Classifier: Topic :: Software Development :: Embedded Systems
